test_sum_pack/__init__.py
test_sum_pack/test_sum.py
test_sum_pack-1.0.0.dist-info/METADATA
test_sum_pack-1.0.0.dist-info/WHEEL
test_sum_pack-1.0.0.dist-info/top_level.txt
test_sum_pack-1.0.0.dist-info/RECORD
