Metadata-Version: 2.1
Name: test_sum_pack
Version: 1.0.0
Summary: simple example of packaging code
Home-page: https://github.com/MuthukumarSubramani/MuthuSub
Author: MuthukumarSubramaniam
Author-email: 
License: MIT
Classifier: Programming Language :: Python :: 3
Classifier: Programming Language :: Python :: 3.11
